nbfigtulz/__init__.py
nbfigtulz/config.py
nbfigtulz/figtools.py
nbfigtulz/thumbnail.py
nbfigtulz-1.0.dist-info/LICENSE.txt
nbfigtulz-1.0.dist-info/METADATA
nbfigtulz-1.0.dist-info/WHEEL
nbfigtulz-1.0.dist-info/top_level.txt
nbfigtulz-1.0.dist-info/RECORD
