Metadata-Version: 2.1
Name: nbfigtulz
Version: 1.0
Summary: Collection of tools to generate and display visualizations in JupyterLab
Home-page: https://github.com/avitase/nbfigtulz
Author: Nis Meinert
Author-email: nis.meinert@gmail.com
License: UNKNOWN
Project-URL: Bug Tracker, https://github.com/avitase/nbfigtulz/issues
Keywords: visualization,jupyterlab
Platform: UNKNOWN
Classifier: Programming Language :: Python :: 3
Classifier: License :: OSI Approved :: MIT License
Classifier: Operating System :: OS Independent
Requires-Python: >=3.8
License-File: LICENSE.txt
Requires-Dist: matplotlib
Requires-Dist: ipython
Requires-Dist: Pillow
